AppleTrailersWrapper/CastCrew.py
AppleTrailersWrapper/Clip.py
AppleTrailersWrapper/ClipVersion.py
AppleTrailersWrapper/Details.py
AppleTrailersWrapper/Featured.py
AppleTrailersWrapper/Hero.py
AppleTrailersWrapper/Locale.py
AppleTrailersWrapper/LocaleHero.py
AppleTrailersWrapper/LocaleHeros.py
AppleTrailersWrapper/Related.py
AppleTrailersWrapper/Review.py
AppleTrailersWrapper/Reviews.py
AppleTrailersWrapper/Search.py
AppleTrailersWrapper/Title.py
AppleTrailersWrapper/__init__.py
AppleTrailersWrapper-1.0.4.dist-info/LICENSE
AppleTrailersWrapper-1.0.4.dist-info/METADATA
AppleTrailersWrapper-1.0.4.dist-info/WHEEL
AppleTrailersWrapper-1.0.4.dist-info/top_level.txt
AppleTrailersWrapper-1.0.4.dist-info/RECORD
