Metadata-Version: 2.1
Name: AppleTrailersWrapper
Version: 1.0.4
Summary: Simple package that wraps Apple Trailers
Home-page: https://github.com/Puyodead1/AppleTrailersWrapper
Author: Puyodead1
Author-email: puyodead@protonmail.com
License: UNKNOWN
Platform: UNKNOWN
Classifier: Programming Language :: Python :: 3
Classifier: License :: OSI Approved :: MIT License
Classifier: Development Status :: 4 - Beta
Requires-Python: >=3
